Flask_MongoNorm-0.2.0.dist-info/DESCRIPTION.rst
Flask_MongoNorm-0.2.0.dist-info/METADATA
Flask_MongoNorm-0.2.0.dist-info/RECORD
Flask_MongoNorm-0.2.0.dist-info/WHEEL
Flask_MongoNorm-0.2.0.dist-info/metadata.json
Flask_MongoNorm-0.2.0.dist-info/top_level.txt
flask_mongonorm/__init__.py
flask_mongonorm/database.py
flask_mongonorm/mongo_client.py
