Metadata-Version: 2.0
Name: Flask-MongoNorm
Version: 0.2.0
Summary: MongoNorm support for Flask applications
Home-page: https://github.com/CrowsT/Flask-MongoNorm
Author: Crows
Author-email: pt.wenhan@gmail.com
License: BSD
Platform: any
Classifier: Development Status :: 3 - Alpha
Classifier: Environment :: Web Environment
Classifier: Intended Audience :: Developers
Classifier: License :: OSI Approved :: BSD License
Classifier: Operating System :: OS Independent
Classifier: Programming Language :: Python
Classifier: Programming Language :: Python :: 3.3
Classifier: Programming Language :: Python :: 3.4
Classifier: Programming Language :: Python :: 3.5
Classifier: Programming Language :: Python :: 3.6
Classifier: Topic :: Internet :: WWW/HTTP :: Dynamic Content
Classifier: Topic :: Software Development :: Libraries :: Python Modules
Requires-Dist: Flask (>=0.10)
Requires-Dist: MongoNorm (>=0.4.0)
Requires-Dist: PyMongo (>=3.0)
